idem_resources_validation/__init__.py
idem_resources_validation/conf.py
idem_resources_validation/version.py
idem_resources_validation/exec/resources_validator/schema/checkers.py
idem_resources_validation/tool/schema/results_collector.py
idem_resources_validation/tool/schema/schema_compatibility_checker.py
idem_resources_validation/tool/schema/scm_utils.py
idem_resources_validation-1.0.0.dist-info/LICENSE
idem_resources_validation-1.0.0.dist-info/METADATA
idem_resources_validation-1.0.0.dist-info/WHEEL
idem_resources_validation-1.0.0.dist-info/top_level.txt
idem_resources_validation-1.0.0.dist-info/RECORD
